Workbook

Sheet Hypothèses
A1: SOLAR WRAP — Hypothèses financières V3 (Jury)
A2: Modèle asset-light : production sous-traitée, réseau d'installation partenaire, priorité au ROI client.
A4: A. Hypothèses générales
A5: Hypothèse | B5: Valeur | C5: Unité | D5: Statut | E5: Source / justification
A6: Taux d'IS | B6: 0.25 | C6: % | D6: Source externe | E6: https://entreprendre.service-public.gouv.fr/vosdroits/F23575
A7: DSO clients | B7: 45 | C7: jours | D7: Hypothèse | E7: Contrats flottes à négocier
A8: Stock moyen | B8: 30 | C8: jours COGS hardware | D8: Hypothèse | E8: Assemblage / sous-traitance + flux tendus
A9: DPO fournisseurs | B9: 45 | C9: jours | D9: Hypothèse | E9: À négocier avec fournisseurs
A10: Attrition parc installé | B10: 0.03 | C10: % / an | D10: Hypothèse | E10: Remplacement / fin de vie
A11: Marge brute SaaS | B11: 0.85 | C11: % | D11: Hypothèse | E11: SOLAR CONTROL
A12: Marge brute services | B12: 0.55 | C12: % | D12: Hypothèse | E12: Ingénierie / intégration
A13: Trésorerie initiale | B13: 250000 | C13: € | D13: Hypothèse | E13: Capital de départ du modèle
A14: Durée amortissement CAPEX | B14: 5 | C14: années | D14: Hypothèse | E14: Linéaire simplifié
A17: B. Hypothèses annuelles — scénario central
A18: Hypothèse | B18: Unité | C18: 2027 | D18: 2028 | E18: 2029 | F18: 2030 | G18: 2031 | H18: 2032 | I18: 2033
A19: Unités vendues | B19: véhicules | C19: 15 | D19: 120 | E19: 450 | F19: 1100 | G19: 2200 | H19: 3500 | I19: 5000
A20: Prix moyen kit + installation | B20: €/véhicule | C20: 6500 | D20: 7500 | E20: 7400 | F20: 7300 | G20: 7200 | H20: 7100 | I20: 7000
A21: COGS complet / véhicule | B21: €/véhicule | C21: 7500 | D21: 5200 | E21: 4900 | F21: 4600 | G21: 4300 | H21: 4100 | I21: 3900
A22: Taux d'attachement SOLAR CONTROL | B22: % | C22: 0 | D22: 0.6 | E22: 0.7 | F22: 0.75 | G22: 0.8 | H22: 0.82 | I22: 0.85
A23: Abonnement SOLAR CONTROL | B23: €/véhicule/an | C23: 0 | D23: 300 | E23: 320 | F23: 330 | G23: 340 | H23: 350 | I23: 360
A24: Revenus services / ingénierie | B24: €/an | C24: 0 | D24: 30000 | E24: 100000 | F24: 200000 | G24: 350000 | H24: 500000 | I24: 700000
A25: Effectif moyen | B25: ETP | C25: 4 | D25: 6 | E25: 9 | F25: 14 | G25: 20 | H25: 28 | I25: 36
A26: Coût chargé moyen / ETP | B26: €/ETP/an | C26: 75000 | D26: 78000 | E26: 80000 | F26: 82000 | G26: 84000 | H26: 86000 | I26: 88000
A27: R&D hors masse salariale | B27: €/an | C27: 400000 | D27: 500000 | E27: 600000 | F27: 700000 | G27: 850000 | H27: 1000000 | I27: 1200000
A28: Sales & Marketing | B28: €/an | C28: 80000 | D28: 180000 | E28: 350000 | F28: 600000 | G28: 900000 | H28: 1300000 | I28: 1800000
A29: G&A | B29: €/an | C29: 120000 | D29: 180000 | E29: 250000 | F29: 350000 | G29: 450000 | H29: 600000 | I29: 750000
... A31: Financement externe | B31: €/an | C31: 1500000 | D31: 1500000 | E31: 1500000 | F31: 0 | G31: 0 | H31: 0 | I31: 0
A34: C. Économie client — hypothèses
A35: Hypothèse | B35: Valeur | C35: Unité | D35: Statut | E35: Source / justification
A36: Économie de gazole | B36: 1800 | C36: L/an | D36: Hypothèse centrale | E36: Fourchette Fraunhofer historique 1 500–2 100 L/an
A37: Valeur économique gazole HT | B37: 1.35 | C37: €/L | D37: Hypothèse prudente | E37: À actualiser selon pays / flotte
A38: Autres économies | B38: 250 | C38: €/an | D38: Hypothèse | E38: Batterie auxiliaire / maintenance
A39: Abonnement SOLAR CONTROL | B39: 300 | C39: €/an | D39: Hypothèse | E39: 25 €/mois
A40: Prix flotte >100 unités | B40: 6900 | C40: €/véhicule | D40: Stratégie commerciale | E40: Remise volume

Sheet Ventes & Marge
A1: SOLAR WRAP — Ventes, parc installé et marge brute
A3: Indicateur | B3: Unité | C3: 2027 | D3: 2028 | E3: 2029 | F3: 2030 | G3: 2031 | H3: 2032 | I3: 2033
A4: Unités vendues | B4: véhicules | C4: =Hypothèses!C19 -> 15 | D4: =Hypothèses!D19 -> 120 | E4: =Hypothèses!E19 -> 450 | F4: =Hypothèses!F19 -> 1100 | G4: =Hypothèses!G19 -> 2200 | H4: =Hypothèses!H19 -> 3500 | I4: =Hypothèses!I19 -> 5000
A5: Prix moyen hardware | B5: €/véhicule | C5: =Hypothèses!C20 -> 6500 | D5: =Hypothèses!D20 -> 7500 | E5: =Hypothèses!E20 -> 7400 | F5: =Hypothèses!F20 -> 7300 | G5: =Hypothèses!G20 -> 7200 | H5: =Hypothèses!H20 -> 7100 | I5: =Hypothèses!I20 -> 7000
A6: CA hardware | B6: k€ | C6: =C4*C5/1000 -> 97.5 | D6: =D4*D5/1000 -> 900 | E6: =E4*E5/1000 -> 3330 | F6: =F4*F5/1000 -> 8030 | G6: =G4*G5/1000 -> 15840 | H6: =H4*H5/1000 -> 24850 | I6: =I4*I5/1000 -> 35000
A7: Parc actif début | B7: véhicules | C7: 0 | D7: =C9 -> 15 | E7: =D9 -> 134.55 | F7: =E9 -> 580.5135 | G7: =F9 -> 1663.0981 | H7: =G9 -> 3813.2052 | I7: =H9 -> 7198.809
A8: Attrition | B8: véhicules | C8: =C7*Hypothèses!$B$10 -> 0 | D8: =D7*Hypothèses!$B$10 -> 0.45 | E8: =E7*Hypothèses!$B$10 -> 4.0365 | F8: =F7*Hypothèses!$B$10 -> 17.415405 | G8: =G7*Hypothèses!$B$10 -> 49.892943 | H8: =H7*Hypothèses!$B$10 -> 114.39615 | I8: =I7*Hypothèses!$B$10 -> 215.96427
A9: Parc actif fin | B9: véhicules | C9: =C7-C8+C4 -> 15 | D9: =D7-D8+D4 -> 134.55 | E9: =E7-E8+E4 -> 580.5135 | F9: =F7-F8+F4 -> 1663.0981 | G9: =G7-G8+G4 -> 3813.2052 | H9: =H7-H8+H4 -> 7198.809 | I9: =I7-I8+I4 -> 11982.845
A10: Parc actif moyen | B10: véhicules | C10: =(C7+C9)/2 -> 7.5 | D10: =(D7+D9)/2 -> 74.775 | E10: =(E7+E9)/2 -> 357.53175 | F10: =(F7+F9)/2 -> 1121.8058 | G10: =(G7+G9)/2 -> 2738.1516 | H10: =(H7+H9)/2 -> 5506.0071 | I10: =(I7+I9)/2 -> 9590.8269
A11: Taux attachement SaaS | B11: % | C11: =Hypothèses!C22 -> 0 | D11: =Hypothèses!D22 -> 0.6 | E11: =Hypothèses!E22 -> 0.7 | F11: =Hypothèses!F22 -> 0.75 | G11: =Hypothèses!G22 -> 0.8 | H11: =Hypothèses!H22 -> 0.82 | I11: =Hypothèses!I22 -> 0.85
A12: Fee SaaS annuel | B12: €/véhicule | C12: =Hypothèses!C23 -> 0 | D12: =Hypothèses!D23 -> 300 | E12: =Hypothèses!E23 -> 320 | F12: =Hypothèses!F23 -> 330 | G12: =Hypothèses!G23 -> 340 | H12: =Hypothèses!H23 -> 350 | I12: =Hypothèses!I23 -> 360
A13: CA SOLAR CONTROL | B13: k€ | C13: =C10*C11*C12/1000 -> 0 | D13: =D10*D11*D12/1000 -> 13.4595 | E13: =E10*E11*E12/1000 -> 80.087112 | F13: =F10*F11*F12/1000 -> 277.64693 | G13: =G10*G11*G12/1000 -> 744.77724 | H13: =H10*H11*H12/1000 -> 1580.224 | I13: =I10*I11*I12/1000 -> 2934.793
A14: CA services / intégration | B14: k€ | C14: =Hypothèses!C24/1000 -> 0 | D14: =Hypothèses!D24/1000 -> 30 | E14: =Hypothèses!E24/1000 -> 100 | F14: =Hypothèses!F24/1000 -> 200 | G14: =Hypothèses!G24/1000 -> 350 | H14: =Hypothèses!H24/1000 -> 500 | I14: =Hypothèses!I24/1000 -> 700
A15: CHIFFRE D'AFFAIRES TOTAL | B15: k€ | C15: =SUM(C6,C13,C14) -> 97.5 | D15: =SUM(D6,D13,D14) -> 943.4595 | E15: =SUM(E6,E13,E14) -> 3510.0871 | F15: =SUM(F6,F13,F14) -> 8507.6469 | G15: =SUM(G6,G13,G14) -> 16934.777 | H15: =SUM(H6,H13,H14) -> 26930.224 | I15: =SUM(I6,I13,I14) -> 38634.793
A16: COGS hardware | B16: k€ | C16: =C4*Hypothèses!C21/1000 -> 112.5 | D16: =D4*Hypothèses!D21/1000 -> 624 | E16: =E4*Hypothèses!E21/1000 -> 2205 | F16: =F4*Hypothèses!F21/1000 -> 5060 | G16: =G4*Hypothèses!G21/1000 -> 9460 | H16: =H4*Hypothèses!H21/1000 -> 14350 | I16: =I4*Hypothèses!I21/1000 -> 19500
A17: COGS SaaS | B17: k€ | C17: =C13*(1-Hypothèses!$B$11) -> 0 | D17: =D13*(1-Hypothèses!$B$11) -> 2.018925 | E17: =E13*(1-Hypothèses!$B$11) -> 12.013067 | F17: =F13*(1-Hypothèses!$B$11) -> 41.64704 | G17: =G13*(1-Hypothèses!$B$11) -> 111.71659 | H17: =H13*(1-Hypothèses!$B$11) -> 237.0336 | I17: =I13*(1-Hypothèses!$B$11) -> 440.21895
A18: COGS services | B18: k€ | C18: =C14*(1-Hypothèses!$B$12) -> 0 | D18: =D14*(1-Hypothèses!$B$12) -> 13.5 | E18: =E14*(1-Hypothèses!$B$12) -> 45 | F18: =F14*(1-Hypothèses!$B$12) -> 90 | G18: =G14*(1-Hypothèses!$B$12) -> 157.5 | H18: =H14*(1-Hypothèses!$B$12) -> 225 | I18: =I14*(1-Hypothèses!$B$12) -> 315
A19: COGS TOTAL | B19: k€ | C19: =SUM(C16:C18) -> 112.5 | D19: =SUM(D16:D18) -> 639.51892 | E19: =SUM(E16:E18) -> 2262.0131 | F19: =SUM(F16:F18) -> 5191.647 | G19: =SUM(G16:G18) -> 9729.2166 | H19: =SUM(H16:H18) -> 14812.034 | I19: =SUM(I16:I18) -> 20255.219
A20: MARGE BRUTE | B20: k€ | C20: =C15-C19 -> -15 | D20: =D15-D19 -> 303.94058 | E20: =E15-E19 -> 1248.074 | F20: =F15-F19 -> 3315.9999 | G20: =G15-G19 -> 7205.5607 | H20: =H15-H19 -> 12118.19 | I20: =I15-I19 -> 18379.574
A21: Marge brute | B21: % | C21: =IFERROR(C20/C15,0) -> -0.15384615 | D21: =IFERROR(D20/D15,0) -> 0.3221554 | E21: =IFERROR(E20/E15,0) -> 0.35556783 | F21: =IFERROR(F20/F15,0) -> 0.38976698 | G21: =IFERROR(G20/G15,0) -> 0.42548895 | H21: =IFERROR(H20/H15,0) -> 0.44998476 | I21: =IFERROR(I20/I15,0) -> 0.47572596

Sheet P&L
A1: SOLAR WRAP — Compte de résultat prévisionnel
A2: Montants en k€ | modèle avant impôt — fiscalité non modélisée car pays d’implantation africain à déterminer
A4: Compte de résultat | B4: Unité | C4: 2027 | D4: 2028 | E4: 2029 | F4: 2030 | G4: 2031 | H4: 2032 | I4: 2033
A5: CHIFFRE D'AFFAIRES | B5: k€ | C5: ='Ventes & Marge'!C15 -> 97.5 | D5: ='Ventes & Marge'!D15 -> 943.4595 | E5: ='Ventes & Marge'!E15 -> 3510.0871 | F5: ='Ventes & Marge'!F15 -> 8507.6469 | G5: ='Ventes & Marge'!G15 -> 16934.777 | H5: ='Ventes & Marge'!H15 -> 26930.224 | I5: ='Ventes & Marge'!I15 -> 38634.793
A6: COGS TOTAL | B6: k€ | C6: ='Ventes & Marge'!C19 -> 112.5 | D6: ='Ventes & Marge'!D19 -> 639.51892 | E6: ='Ventes & Marge'!E19 -> 2262.0131 | F6: ='Ventes & Marge'!F19 -> 5191.647 | G6: ='Ventes & Marge'!G19 -> 9729.2166 | H6: ='Ventes & Marge'!H19 -> 14812.034 | I6: ='Ventes & Marge'!I19 -> 20255.219
A7: MARGE BRUTE | B7: k€ | C7: =C5-C6 -> -15 | D7: =D5-D6 -> 303.94058 | E7: =E5-E6 -> 1248.074 | F7: =F5-F6 -> 3315.9999 | G7: =G5-G6 -> 7205.5607 | H7: =H5-H6 -> 12118.19 | I7: =I5-I6 -> 18379.574
A8: Marge brute | B8: % | C8: =IFERROR(C7/C5,0) -> -0.15384615 | D8: =IFERROR(D7/D5,0) -> 0.3221554 | E8: =IFERROR(E7/E5,0) -> 0.35556783 | F8: =IFERROR(F7/F5,0) -> 0.38976698 | G8: =IFERROR(G7/G5,0) -> 0.42548895 | H8: =IFERROR(H7/H5,0) -> 0.44998476 | I8: =IFERROR(I7/I5,0) -> 0.47572596
A9: Masse salariale | B9: k€ | C9: =Hypothèses!C25*Hypothèses!C26/1000 -> 300 | D9: =Hypothèses!D25*Hypothèses!D26/1000 -> 468 | E9: =Hypothèses!E25*Hypothèses!E26/1000 -> 720 | F9: =Hypothèses!F25*Hypothèses!F26/1000 -> 1148 | G9: =Hypothèses!G25*Hypothèses!G26/1000 -> 1680 | H9: =Hypothèses!H25*Hypothèses!H26/1000 -> 2408 | I9: =Hypothèses!I25*Hypothèses!I26/1000 -> 3168
A10: R&D hors payroll | B10: k€ | C10: =Hypothèses!C27/1000 -> 400 | D10: =Hypothèses!D27/1000 -> 500 | E10: =Hypothèses!E27/1000 -> 600 | F10: =Hypothèses!F27/1000 -> 700 | G10: =Hypothèses!G27/1000 -> 850 | H10: =Hypothèses!H27/1000 -> 1000 | I10: =Hypothèses!I27/1000 -> 1200
A11: Sales & Marketing | B11: k€ | C11: =Hypothèses!C28/1000 -> 80 | D11: =Hypothèses!D28/1000 -> 180 | E11: =Hypothèses!E28/1000 -> 350 | F11: =Hypothèses!F28/1000 -> 600 | G11: =Hypothèses!G28/1000 -> 900 | H11: =Hypothèses!H28/1000 -> 1300 | I11: =Hypothèses!I28/1000 -> 1800
A12: G&A | B12: k€ | C12: =Hypothèses!C29/1000 -> 120 | D12: =Hypothèses!D29/1000 -> 180 | E12: =Hypothèses!E29/1000 -> 250 | F12: =Hypothèses!F29/1000 -> 350 | G12: =Hypothèses!G29/1000 -> 450 | H12: =Hypothèses!H29/1000 -> 600 | I12: =Hypothèses!I29/1000 -> 750
A13: OPEX CASH | B13: k€ | C13: =SUM(C9:C12) -> 900 | D13: =SUM(D9:D12) -> 1328 | E13: =SUM(E9:E12) -> 1920 | F13: =SUM(F9:F12) -> 2798 | G13: =SUM(G9:G12) -> 3880 | H13: =SUM(H9:H12) -> 5308 | I13: =SUM(I9:I12) -> 6918
A14: EBITDA | B14: k€ | C14: =C7-C13 -> -915 | D14: =D7-D13 -> -1024.0594 | E14: =E7-E13 -> -671.92595 | F14: =F7-F13 -> 517.99989 | G14: =G7-G13 -> 3325.5607 | H14: =H7-H13 -> 6810.1904 | I14: =I7-I13 -> 11461.574
A15: Marge EBITDA | B15: % | C15: =IFERROR(C14/C5,0) -> -9.3846154 | D15: =IFERROR(D14/D5,0) -> -1.0854302 | E15: =IFERROR(E14/E5,0) -> -0.19142715 | F15: =IFERROR(F14/F5,0) -> 0.060886388 | G15: =IFERROR(G14/G5,0) -> 0.19637463 | H15: =IFERROR(H14/H5,0) -> 0.2528828 | I15: =IFERROR(I14/I5,0) -> 0.29666457
A16: Amortissements | B16: k€ | C16: =SUM(Hypothèses!C30)/Hypothèses!$B$14/1000 -> 40 | D16: =SUM(Hypothèses!C30,Hypothèses!D30)/Hypothèses!$B$14/1000 -> 90 | E16: =SUM(Hypothèses!C30,Hypothèses!D30,Hypothèses!E30)/Hypothèses!$B$14/1000 -> 150 | F16: =SUM(Hypothèses!C30,Hypothèses!D30,Hypothèses!E30,Hypothèses!F30)/Hypothèses!$B$14/1000 -> 230 | G16: =SUM(Hypothèses!C30,Hypothèses!D30,Hypothèses!E30,Hypothèses!F30,Hypothèses!G30)/Hypothèses!$B$14/1000 -> 330 | H16: =SUM(Hypothèses!D30,Hypothèses!E30,Hypothèses!F30,Hypothèses!G30,Hypothèses!H30)/Hypothèses!$B$14/1000 -> 410 | I16: =SUM(Hypothèses!E30,Hypothèses!F30,Hypothèses!G30,Hypothèses!H30,Hypothèses!I30)/Hypothèses!$B$14/1000 -> 500
A17: EBIT | B17: k€ | C17: =C14-C16 -> -955 | D17: =D14-D16 -> -1114.0594 | E17: =E14-E16 -> -821.92595 | F17: =F14-F16 -> 287.99989 | G17: =G14-G16 -> 2995.5607 | H17: =H14-H16 -> 6400.1904 | I17: =I14-I16 -> 10961.574
A18: Résultat opérationnel avant impôt | B18: k€ | C18: =C17 -> -955 | D18: =D17 -> -1114.0594 | E18: =E17 -> -821.92595 | F18: =F17 -> 287.99989 | G18: =G17 -> 2995.5607 | H18: =H17 -> 6400.1904 | I18: =I17 -> 10961.574
A19: Fiscalité | C19: Non modélisée | D19: Non modélisée | E19: Non modélisée | F19: Non modélisée | G19: Non modélisée | H19: Non modélisée | I19: Non modélisée
A20: IS modélisé | B20: k€ | C20: 0 | D20: 0 | E20: 0 | F20: 0 | G20: 0 | H20: 0 | I20: 0
A21: RÉSULTAT AVANT IMPÔT | B21: k€ | C21: =C18 -> -955 | D21: =D18 -> -1114.0594 | E21: =E18 -> -821.92595 | F21: =F18 -> 287.99989 | G21: =G18 -> 2995.5607 | H21: =H18 -> 6400.1904 | I21: =I18 -> 10961.574

Sheet Cash Flow
A1: SOLAR WRAP — Trésorerie & besoin de financement
A3: Cash Flow | B3: Unité | C3: 2027 | D3: 2028 | E3: 2029 | F3: 2030 | G3: 2031 | H3: 2032 | I3: 2033
A4: EBITDA | B4: k€ | C4: ='P&L'!C14 -> -915 | D4: ='P&L'!D14 -> -1024.0594 | E4: ='P&L'!E14 -> -671.92595 | F4: ='P&L'!F14 -> 517.99989 | G4: ='P&L'!G14 -> 3325.5607 | H4: ='P&L'!H14 -> 6810.1904 | I4: ='P&L'!I14 -> 11461.574
A5: IS payé | B5: k€ | C5: 0 | D5: 0 | E5: 0 | F5: 0 | G5: 0 | H5: 0 | I5: 0
A6: CAPEX | B6: k€ | C6: =Hypothèses!C30/1000 -> 200 | D6: =Hypothèses!D30/1000 -> 250 | E6: =Hypothèses!E30/1000 -> 300 | F6: =Hypothèses!F30/1000 -> 400 | G6: =Hypothèses!G30/1000 -> 500 | H6: =Hypothèses!H30/1000 -> 600 | I6: =Hypothèses!I30/1000 -> 700
A7: Créances clients | B7: k€ | C7: ='Ventes & Marge'!C15*Hypothèses!$B$7/365 -> 12.020548 | D7: ='Ventes & Marge'!D15*Hypothèses!$B$7/365 -> 116.31692 | E7: ='Ventes & Marge'!E15*Hypothèses!$B$7/365 -> 432.75047 | F7: ='Ventes & Marge'!F15*Hypothèses!$B$7/365 -> 1048.888 | G7: ='Ventes & Marge'!G15*Hypothèses!$B$7/365 -> 2087.8492 | H7: ='Ventes & Marge'!H15*Hypothèses!$B$7/365 -> 3320.1646 | I7: ='Ventes & Marge'!I15*Hypothèses!$B$7/365 -> 4763.1937
A8: Stock | B8: k€ | C8: ='Ventes & Marge'!C16*Hypothèses!$B$8/365 -> 9.2465753 | D8: ='Ventes & Marge'!D16*Hypothèses!$B$8/365 -> 51.287671 | E8: ='Ventes & Marge'!E16*Hypothèses!$B$8/365 -> 181.23288 | F8: ='Ventes & Marge'!F16*Hypothèses!$B$8/365 -> 415.89041 | G8: ='Ventes & Marge'!G16*Hypothèses!$B$8/365 -> 777.53425 | H8: ='Ventes & Marge'!H16*Hypothèses!$B$8/365 -> 1179.4521 | I8: ='Ventes & Marge'!I16*Hypothèses!$B$8/365 -> 1602.7397
A9: Dettes fournisseurs | B9: k€ | C9: ='Ventes & Marge'!C19*Hypothèses!$B$9/365 -> 13.869863 | D9: ='Ventes & Marge'!D19*Hypothèses!$B$9/365 -> 78.844799 | E9: ='Ventes & Marge'!E19*Hypothèses!$B$9/365 -> 278.87832 | F9: ='Ventes & Marge'!F19*Hypothèses!$B$9/365 -> 640.06607 | G9: ='Ventes & Marge'!G19*Hypothèses!$B$9/365 -> 1199.4925 | H9: ='Ventes & Marge'!H19*Hypothèses!$B$9/365 -> 1826.1411 | I9: ='Ventes & Marge'!I19*Hypothèses!$B$9/365 -> 2497.2188
A10: BFR net | B10: k€ | C10: =C7+C8-C9 -> 7.3972603 | D10: =D7+D8-D9 -> 88.759797 | E10: =E7+E8-E9 -> 335.10502 | F10: =F7+F8-F9 -> 824.71232 | G10: =G7+G8-G9 -> 1665.891 | H10: =H7+H8-H9 -> 2673.4755 | I10: =I7+I8-I9 -> 3868.7146
A11: Variation BFR | B11: k€ | C11: =C10 -> 7.3972603 | D11: =D10-C10 -> 81.362537 | E11: =E10-D10 -> 246.34522 | F11: =F10-E10 -> 489.6073 | G11: =G10-F10 -> 841.17872 | H11: =H10-G10 -> 1007.5845 | I11: =I10-H10 -> 1195.2391
A12: FREE CASH FLOW AVANT FINANCEMENT | B12: k€ | C12: =C4-C5-C6-C11 -> -1122.3973 | D12: =D4-D5-D6-D11 -> -1355.422 | E12: =E4-E5-E6-E11 -> -1218.2712 | F12: =F4-F5-F6-F11 -> -371.6074 | G12: =G4-G5-G6-G11 -> 1984.3819 | H12: =H4-H5-H6-H11 -> 5202.6059 | I12: =I4-I5-I6-I11 -> 9566.335
A13: Trésorerie ouverture | B13: k€ | C13: =Hypothèses!$B$13/1000 -> 250 | D13: =C15 -> 627.60274 | E13: =D15 -> 772.18078 | F13: =E15 -> 1053.9096 | G13: =F15 -> 682.3022 | H13: =G15 -> 2666.6841 | I13: =H15 -> 7869.2901
A14: Financement externe | B14: k€ | C14: =Hypothèses!C31/1000 -> 1500 | D14: =Hypothèses!D31/1000 -> 1500 | E14: =Hypothèses!E31/1000 -> 1500 | F14: =Hypothèses!F31/1000 -> 0 | G14: =Hypothèses!G31/1000 -> 0 | H14: =Hypothèses!H31/1000 -> 0 | I14: =Hypothèses!I31/1000 -> 0
A15: TRÉSORERIE CLÔTURE | B15: k€ | C15: =C13+C12+C14 -> 627.60274 | D15: =D13+D12+D14 -> 772.18078 | E15: =E13+E12+E14 -> 1053.9096 | F15: =F13+F12+F14 -> 682.3022 | G15: =G13+G12+G14 -> 2666.6841 | H15: =H13+H12+H14 -> 7869.2901 | I15: =I13+I12+I14 -> 17435.625
A17: Note : le modèle est présenté avant impôt. L’IS sera intégré après choix du pays d’implantation et validation du régime fiscal local.

Sheet ROI Client
A1: SOLAR WRAP — ROI client & stratégie de prix
A3: A. Cas client standard
A4: Prix client standard | B4: € | C4: =Hypothèses!D20 -> 7500
A5: Économie gazole | B5: L/an | C5: =Hypothèses!$B$36 -> 1800
A6: Valeur gazole HT | B6: €/L | C6: =Hypothèses!$B$37 -> 1.35
A7: Économie carburant | B7: €/an | C7: =C5*C6 -> 2430
A8: Autres économies | B8: €/an | C8: =Hypothèses!$B$38 -> 250
A9: Abonnement SOLAR CONTROL | B9: €/an | C9: =Hypothèses!$B$39 -> 300
A10: Économies nettes annuelles | B10: €/an | C10: =C7+C8-C9 -> 2380
A11: Payback client standard | B11: années | C11: =C4/C10 -> 3.1512605
A14: B. Offre flotte >100 unités
A15: Prix flotte | B15: € | C15: =Hypothèses!$B$40 -> 6900
A16: Payback flotte | B16: années | C16: =C15/C10 -> 2.8991597
A17: Objectif commercial | C17: < 3 ans
A20: C. Lecture jury
A21: Proposition | B21: Prix | C21: Revenu récurrent | D21: Payback | E21: Logique | F21: Message
A22: Standard | B22: 7 500 € | C22: 25 €/mois | D22: ≈ 3,2 ans | E22: Marge + preuve de valeur | F22: Prix de lancement
A23: Flotte >100 | B23: 6 900 € | C23: 25 €/mois | D23: ≈ 2,9 ans | E23: Volume / coût unitaire réduit | F23: Accélérer les grands comptes
A24: Industrialisation | B24: Prix décroissant | C24: SaaS croissant | D24: < 3 ans cible | E24: COGS ↓ par volume | F24: Scalable sans usine lourde

Sheet Dashboard Jury
A1: SOLAR WRAP — FINANCIAL CASE FOR JURY
A2: Version jury : modèle avant impôt, fiscalité locale à intégrer après choix du pays africain d’implantation.
A3: Prix lancement | C3: Payback client | E3: Financement total | G3: EBITDA positif
A4: =Hypothèses!D20 -> 7500 | C4: ='ROI Client'!C11 -> 3.1512605 | E4: =SUM(Hypothèses!C31:I31) -> 4500000 | G4: ="2030" -> 2030
A7: CA 2033 | C7: EBITDA 2033 | E7: Marge EBITDA 2033 | G7: Fee Cash Flow positif
A8: ='P&L'!I5*1000 -> 38634793 | C8: ='P&L'!I14*1000 -> 11461574 | E8: ='P&L'!I15 -> 0.29666457 | G8: ="2031" -> 2031
A13: Trajectoire financière
A14: Indicateur | B14: 2027 | C14: 2028 | D14: 2029 | E14: 2030 | F14: 2031 | G14: 2032 | H14: 2033
A15: CA (M€) | B15: ='P&L'!C5/1000 -> 0.0975 | C15: ='P&L'!D5/1000 -> 0.9434595 | D15: ='P&L'!E5/1000 -> 3.5100871 | E15: ='P&L'!F5/1000 -> 8.5076469 | F15: ='P&L'!G5/1000 -> 16.934777 | G15: ='P&L'!H5/1000 -> 26.930224 | H15: ='P&L'!I5/1000 -> 38.634793
A16: EBITDA (M€) | B16: ='P&L'!C14/1000 -> -0.915 | C16: ='P&L'!D14/1000 -> -1.0240594 | D16: ='P&L'!E14/1000 -> -0.67192595 | E16: ='P&L'!F14/1000 -> 0.51799989 | F16: ='P&L'!G14/1000 -> 3.3255607 | G16: ='P&L'!H14/1000 -> 6.8101904 | H16: ='P&L'!I14/1000 -> 11.461574
A36: Message financier à défendre devant le jury
A37: 1) Prix de lancement à 7 500 € grâce à un modèle asset-light et à la standardisation du kit. 2) Payback client autour de 3 ans, avec une offre flotte à 6 900 €. 3) EBITDA positif en 2030 et FCF positif en 2031. 4) Besoin de financement de 4,5 M€ en trois tranches ; la trésorerie reste positive dans le scénario central. 5) En 2033, le modèle atteint environ 38,6 M€ de CA et 11,5 M€ d’EBITDA. 6) Le modèle est volontairement présenté avant impôt : la fiscalité sera modélisée pays par pays une fois le pays d’implantation africain retenu.
A45: FCF = Free Cash Flow, en français flux de trésorerie disponible.
A47: C’est l’argent que l’entreprise génère réellement après avoir payé ses dépenses d’exploitation et ses investissements.
A49: Dans votre modèle Solar Wrap, on le calcule simplement comme :
A51: FCF = EBITDA – CAPEX – variation du BFR – impôts éventuels
A53: Dans la version Afrique que nous avons retenue pour le jury, nous avons présenté le modèle avant impôt, donc :
A55: FCF = EBITDA – CAPEX – variation du BFR
A57: Exemple 2031 dans votre fichier :
A59: EBITDA : environ 3,33 M€
A60: CAPEX : 0,50 M€
A61: hausse du BFR : environ 0,84 M€
... A67: Cela veut dire qu’en 2031, après avoir financé son fonctionnement, ses investissements et sa croissance, Solar Wrap génère encore environ 2 M€ de cash disponible.
